<?xml version="1.0"?>
<ownershipDocument>

    <schemaVersion>X0306</schemaVersion>

    <documentType>4</documentType>

    <periodOfReport>2018-12-17</periodOfReport>

    <issuer>
        <issuerCik>0001118237</issuerCik>
        <issuerName>MBT FINANCIAL CORP</issuerName>
        <issuerTradingSymbol>MBTF</issuerTradingSymbol>
    </issuer>

    <reportingOwner>
        <reportingOwnerId>
            <rptOwnerCik>0001244299</rptOwnerCik>
            <rptOwnerName>CHAFFIN H DOUGLAS</rptOwnerName>
        </reportingOwnerId>
        <reportingOwnerAddress>
            <rptOwnerStreet1>102 E. FRONT ST.</rptOwnerStreet1>
            <rptOwnerStreet2></rptOwnerStreet2>
            <rptOwnerCity>MONROE</rptOwnerCity>
            <rptOwnerState>MI</rptOwnerState>
            <rptOwnerZipCode>48161</rptOwnerZipCode>
            <rptOwnerStateDescription></rptOwnerStateDescription>
        </reportingOwnerAddress>
        <reportingOwnerRelationship>
            <isDirector>1</isDirector>
            <isOfficer>1</isOfficer>
            <officerTitle>President &amp; CEO</officerTitle>
        </reportingOwnerRelationship>
    </reportingOwner>

    <nonDerivativeTable>
        <nonDerivativeTransaction>
            <securityTitle>
                <value>Common Stock</value>
            </securityTitle>
            <transactionDate>
                <value>2018-12-17</value>
            </transactionDate>
            <transactionCoding>
                <transactionFormType>4</transactionFormType>
                <transactionCode>A</transactionCode>
                <equitySwapInvolved>0</equitySwapInvolved>
            </transactionCoding>
            <transactionAmounts>
                <transactionShares>
                    <value>12535</value>
                </transactionShares>
                <transactionPricePerShare>
                    <value>0</value>
                </transactionPricePerShare>
                <transactionAcquiredDisposedCode>
                    <value>A</value>
                </transactionAcquiredDisposedCode>
            </transactionAmounts>
            <postTransactionAmounts>
                <sharesOwnedFollowingTransaction>
                    <value>193551</value>
                </sharesOwnedFollowingTransaction>
            </postTransactionAmounts>
            <ownershipNature>
                <directOrIndirectOwnership>
                    <value>D</value>
                </directOrIndirectOwnership>
            </ownershipNature>
        </nonDerivativeTransaction>
        <nonDerivativeTransaction>
            <securityTitle>
                <value>Common Stock</value>
            </securityTitle>
            <transactionDate>
                <value>2018-12-17</value>
            </transactionDate>
            <transactionCoding>
                <transactionFormType>4</transactionFormType>
                <transactionCode>D</transactionCode>
                <equitySwapInvolved>0</equitySwapInvolved>
            </transactionCoding>
            <transactionAmounts>
                <transactionShares>
                    <value>3586</value>
                </transactionShares>
                <transactionPricePerShare>
                    <value>10.04</value>
                </transactionPricePerShare>
                <transactionAcquiredDisposedCode>
                    <value>D</value>
                </transactionAcquiredDisposedCode>
            </transactionAmounts>
            <postTransactionAmounts>
                <sharesOwnedFollowingTransaction>
                    <value>189965</value>
                </sharesOwnedFollowingTransaction>
            </postTransactionAmounts>
            <ownershipNature>
                <directOrIndirectOwnership>
                    <value>D</value>
                </directOrIndirectOwnership>
            </ownershipNature>
        </nonDerivativeTransaction>
    </nonDerivativeTable>

    <ownerSignature>
        <signatureName>/s/ H. Douglas Chaffin</signatureName>
        <signatureDate>2018-12-18</signatureDate>
    </ownerSignature>
</ownershipDocument>
