<?xml version="1.0"?>
<ownershipDocument>

    <schemaVersion>X0206</schemaVersion>

    <documentType>3</documentType>

    <periodOfReport>2019-01-04</periodOfReport>

    <noSecuritiesOwned>1</noSecuritiesOwned>

    <issuer>
        <issuerCik>0001446847</issuerCik>
        <issuerName>IRONWOOD PHARMACEUTICALS INC</issuerName>
        <issuerTradingSymbol>IRWD</issuerTradingSymbol>
    </issuer>

    <reportingOwner>
        <reportingOwnerId>
            <rptOwnerCik>0001763533</rptOwnerCik>
            <rptOwnerName>Mallon Mark</rptOwnerName>
        </reportingOwnerId>
        <reportingOwnerAddress>
            <rptOwnerStreet1>C/O IRONWOOD PHARMACEUTICALS, INC.</rptOwnerStreet1>
            <rptOwnerStreet2>301 BINNEY STREET</rptOwnerStreet2>
            <rptOwnerCity>CAMBRIDGE</rptOwnerCity>
            <rptOwnerState>MA</rptOwnerState>
            <rptOwnerZipCode>02142</rptOwnerZipCode>
            <rptOwnerStateDescription></rptOwnerStateDescription>
        </reportingOwnerAddress>
        <reportingOwnerRelationship>
            <isDirector>0</isDirector>
            <isOfficer>1</isOfficer>
            <isTenPercentOwner>0</isTenPercentOwner>
            <isOther>0</isOther>
            <officerTitle>Executive Senior Advisor</officerTitle>
        </reportingOwnerRelationship>
    </reportingOwner>

    <footnotes></footnotes>

    <remarks>Exhibit 24: Power of Attorney</remarks>

    <ownerSignature>
        <signatureName>/s/ Conor Kilroy, Attorney-in-Fact</signatureName>
        <signatureDate>2019-01-11</signatureDate>
    </ownerSignature>
</ownershipDocument>
