<?xml version="1.0"?>
<ownershipDocument>

    <schemaVersion>X0306</schemaVersion>

    <documentType>4</documentType>

    <periodOfReport>2018-12-11</periodOfReport>

    <issuer>
        <issuerCik>0001649744</issuerCik>
        <issuerName>DULUTH HOLDINGS INC.</issuerName>
        <issuerTradingSymbol>DLTH</issuerTradingSymbol>
    </issuer>

    <reportingOwner>
        <reportingOwnerId>
            <rptOwnerCik>0001648407</rptOwnerCik>
            <rptOwnerName>SCHLECHT STEPHEN L.</rptOwnerName>
        </reportingOwnerId>
        <reportingOwnerAddress>
            <rptOwnerStreet1>201 EAST FRONT STREET</rptOwnerStreet1>
            <rptOwnerStreet2></rptOwnerStreet2>
            <rptOwnerCity>MOUNT HOREB</rptOwnerCity>
            <rptOwnerState>WI</rptOwnerState>
            <rptOwnerZipCode>53572</rptOwnerZipCode>
            <rptOwnerStateDescription></rptOwnerStateDescription>
        </reportingOwnerAddress>
        <reportingOwnerRelationship>
            <isDirector>1</isDirector>
            <isOfficer>1</isOfficer>
            <isTenPercentOwner>1</isTenPercentOwner>
            <isOther>0</isOther>
            <officerTitle>Executive Chairman</officerTitle>
        </reportingOwnerRelationship>
    </reportingOwner>

    <nonDerivativeTable>
        <nonDerivativeTransaction>
            <securityTitle>
                <value>Class B Common Stock</value>
            </securityTitle>
            <transactionDate>
                <value>2018-12-11</value>
            </transactionDate>
            <transactionCoding>
                <transactionFormType>5</transactionFormType>
                <transactionCode>G</transactionCode>
                <equitySwapInvolved>0</equitySwapInvolved>
            </transactionCoding>
            <transactionAmounts>
                <transactionShares>
                    <value>399201</value>
                </transactionShares>
                <transactionPricePerShare>
                    <value>0</value>
                    <footnoteId id="F1"/>
                </transactionPricePerShare>
                <transactionAcquiredDisposedCode>
                    <value>D</value>
                </transactionAcquiredDisposedCode>
            </transactionAmounts>
            <postTransactionAmounts>
                <sharesOwnedFollowingTransaction>
                    <value>8126705</value>
                </sharesOwnedFollowingTransaction>
            </postTransactionAmounts>
            <ownershipNature>
                <directOrIndirectOwnership>
                    <value>D</value>
                </directOrIndirectOwnership>
                <natureOfOwnership>
                    <value></value>
                </natureOfOwnership>
            </ownershipNature>
        </nonDerivativeTransaction>
    </nonDerivativeTable>

    <footnotes>
        <footnote id="F1">Transaction is a gift, therefore price is not applicable.</footnote>
    </footnotes>

    <remarks></remarks>

    <ownerSignature>
        <signatureName>Dennis F. Connolly (pursuant to Power of Attorney previously filed)</signatureName>
        <signatureDate>2018-12-13</signatureDate>
    </ownerSignature>
</ownershipDocument>
