<?xml version="1.0"?>
<ownershipDocument>

    <schemaVersion>X0306</schemaVersion>

    <documentType>4</documentType>

    <periodOfReport>2019-01-07</periodOfReport>

    <notSubjectToSection16>0</notSubjectToSection16>

    <issuer>
        <issuerCik>0001654151</issuerCik>
        <issuerName>Deciphera Pharmaceuticals, Inc.</issuerName>
        <issuerTradingSymbol>DCPH</issuerTradingSymbol>
    </issuer>

    <reportingOwner>
        <reportingOwnerId>
            <rptOwnerCik>0001410514</rptOwnerCik>
            <rptOwnerName>Kelly Thomas Patrick</rptOwnerName>
        </reportingOwnerId>
        <reportingOwnerAddress>
            <rptOwnerStreet1>C/O DECIPHERA PHARMACEUTICALS, INC.</rptOwnerStreet1>
            <rptOwnerStreet2>500 TOTTEN POND ROAD</rptOwnerStreet2>
            <rptOwnerCity>WALTHAM</rptOwnerCity>
            <rptOwnerState>MA</rptOwnerState>
            <rptOwnerZipCode>02451</rptOwnerZipCode>
            <rptOwnerStateDescription></rptOwnerStateDescription>
        </reportingOwnerAddress>
        <reportingOwnerRelationship>
            <isDirector>0</isDirector>
            <isOfficer>1</isOfficer>
            <isTenPercentOwner>0</isTenPercentOwner>
            <isOther>0</isOther>
            <officerTitle>Chief Financial Officer</officerTitle>
        </reportingOwnerRelationship>
    </reportingOwner>

    <nonDerivativeTable>
        <nonDerivativeTransaction>
            <securityTitle>
                <value>Common Stock</value>
            </securityTitle>
            <transactionDate>
                <value>2019-01-07</value>
            </transactionDate>
            <deemedExecutionDate></deemedExecutionDate>
            <transactionCoding>
                <transactionFormType>4</transactionFormType>
                <transactionCode>M</transactionCode>
                <equitySwapInvolved>0</equitySwapInvolved>
            </transactionCoding>
            <transactionTimeliness>
                <value></value>
            </transactionTimeliness>
            <transactionAmounts>
                <transactionShares>
                    <value>5000</value>
                </transactionShares>
                <transactionPricePerShare>
                    <value>1.89</value>
                </transactionPricePerShare>
                <transactionAcquiredDisposedCode>
                    <value>A</value>
                </transactionAcquiredDisposedCode>
            </transactionAmounts>
            <postTransactionAmounts>
                <sharesOwnedFollowingTransaction>
                    <value>5000</value>
                </sharesOwnedFollowingTransaction>
            </postTransactionAmounts>
            <ownershipNature>
                <directOrIndirectOwnership>
                    <value>D</value>
                </directOrIndirectOwnership>
            </ownershipNature>
        </nonDerivativeTransaction>
        <nonDerivativeTransaction>
            <securityTitle>
                <value>Common Stock</value>
            </securityTitle>
            <transactionDate>
                <value>2019-01-07</value>
            </transactionDate>
            <deemedExecutionDate></deemedExecutionDate>
            <transactionCoding>
                <transactionFormType>4</transactionFormType>
                <transactionCode>S</transactionCode>
                <equitySwapInvolved>0</equitySwapInvolved>
                <footnoteId id="F1"/>
            </transactionCoding>
            <transactionTimeliness>
                <value></value>
            </transactionTimeliness>
            <transactionAmounts>
                <transactionShares>
                    <value>5000</value>
                </transactionShares>
                <transactionPricePerShare>
                    <value>25.18</value>
                    <footnoteId id="F2"/>
                </transactionPricePerShare>
                <transactionAcquiredDisposedCode>
                    <value>D</value>
                </transactionAcquiredDisposedCode>
            </transactionAmounts>
            <postTransactionAmounts>
                <sharesOwnedFollowingTransaction>
                    <value>0</value>
                </sharesOwnedFollowingTransaction>
            </postTransactionAmounts>
            <ownershipNature>
                <directOrIndirectOwnership>
                    <value>D</value>
                </directOrIndirectOwnership>
            </ownershipNature>
        </nonDerivativeTransaction>
    </nonDerivativeTable>

    <derivativeTable>
        <derivativeTransaction>
            <securityTitle>
                <value>Stock Option (Right to Buy)</value>
            </securityTitle>
            <conversionOrExercisePrice>
                <value>1.89</value>
            </conversionOrExercisePrice>
            <transactionDate>
                <value>2019-01-07</value>
            </transactionDate>
            <deemedExecutionDate></deemedExecutionDate>
            <transactionCoding>
                <transactionFormType>4</transactionFormType>
                <transactionCode>M</transactionCode>
                <equitySwapInvolved>0</equitySwapInvolved>
            </transactionCoding>
            <transactionTimeliness>
                <value></value>
            </transactionTimeliness>
            <transactionAmounts>
                <transactionShares>
                    <value>5000</value>
                </transactionShares>
                <transactionPricePerShare>
                    <value>0.00</value>
                </transactionPricePerShare>
                <transactionAcquiredDisposedCode>
                    <value>D</value>
                </transactionAcquiredDisposedCode>
            </transactionAmounts>
            <exerciseDate>
                <footnoteId id="F3"/>
            </exerciseDate>
            <expirationDate>
                <value>2025-12-17</value>
            </expirationDate>
            <underlyingSecurity>
                <underlyingSecurityTitle>
                    <value>Common Stock</value>
                </underlyingSecurityTitle>
                <underlyingSecurityShares>
                    <value>5000</value>
                </underlyingSecurityShares>
            </underlyingSecurity>
            <postTransactionAmounts>
                <sharesOwnedFollowingTransaction>
                    <value>168008</value>
                </sharesOwnedFollowingTransaction>
            </postTransactionAmounts>
            <ownershipNature>
                <directOrIndirectOwnership>
                    <value>D</value>
                </directOrIndirectOwnership>
            </ownershipNature>
        </derivativeTransaction>
    </derivativeTable>

    <footnotes>
        <footnote id="F1">The sale was effected pursuant to a Rule 10b5-1 trading plan adopted by the Reporting Person.</footnote>
        <footnote id="F2">The price reported in Column 4 is a weighted average price. These shares were sold in multiple transactions at prices ranging from $25.00 to $25.39. The Reporting Person undertakes to provide to the Issuer, any
security holder of the Issuer, or the staff at the Securities and Exchange Commission, upon request, full information regarding the number of shares sold at each separate price within the range.</footnote>
        <footnote id="F3">This stock option award was issued pursuant to Deciphera Pharmaceuticals, LLC's 2015 Equity Incentive Plan. The option vests in 16 equal installments over a 4-year period following the vesting commencement date of 2/23/2015, subject to continued service through such dates.</footnote>
    </footnotes>

    <remarks></remarks>

    <ownerSignature>
        <signatureName>/s/ Thomas P. Kelly</signatureName>
        <signatureDate>2019-01-09</signatureDate>
    </ownerSignature>
</ownershipDocument>
