<?xml version="1.0"?>
<ownershipDocument>

    <schemaVersion>X0306</schemaVersion>

    <documentType>4</documentType>

    <periodOfReport>2018-12-10</periodOfReport>

    <notSubjectToSection16>0</notSubjectToSection16>

    <issuer>
        <issuerCik>0000059478</issuerCik>
        <issuerName>LILLY ELI &amp; CO</issuerName>
        <issuerTradingSymbol>LLY</issuerTradingSymbol>
    </issuer>

    <reportingOwner>
        <reportingOwnerId>
            <rptOwnerCik>0001725140</rptOwnerCik>
            <rptOwnerName>O'Neill Myles</rptOwnerName>
        </reportingOwnerId>
        <reportingOwnerAddress>
            <rptOwnerStreet1>LILLY CORPORATE CENTER</rptOwnerStreet1>
            <rptOwnerStreet2></rptOwnerStreet2>
            <rptOwnerCity>INDIANAPOLIS</rptOwnerCity>
            <rptOwnerState>IN</rptOwnerState>
            <rptOwnerZipCode>46285</rptOwnerZipCode>
            <rptOwnerStateDescription></rptOwnerStateDescription>
        </reportingOwnerAddress>
        <reportingOwnerRelationship>
            <isDirector>0</isDirector>
            <isOfficer>1</isOfficer>
            <isTenPercentOwner>0</isTenPercentOwner>
            <isOther>0</isOther>
            <officerTitle>SVP &amp; Pres., Mfg. Operations</officerTitle>
            <otherText></otherText>
        </reportingOwnerRelationship>
    </reportingOwner>

    <nonDerivativeTable>
        <nonDerivativeTransaction>
            <securityTitle>
                <value>Common Stock</value>
            </securityTitle>
            <transactionDate>
                <value>2018-12-10</value>
            </transactionDate>
            <transactionCoding>
                <transactionFormType>4</transactionFormType>
                <transactionCode>S</transactionCode>
                <equitySwapInvolved>0</equitySwapInvolved>
                <footnoteId id="F1"/>
            </transactionCoding>
            <transactionAmounts>
                <transactionShares>
                    <value>19300</value>
                </transactionShares>
                <transactionPricePerShare>
                    <value>112.72</value>
                    <footnoteId id="F2"/>
                </transactionPricePerShare>
                <transactionAcquiredDisposedCode>
                    <value>D</value>
                </transactionAcquiredDisposedCode>
            </transactionAmounts>
            <postTransactionAmounts>
                <sharesOwnedFollowingTransaction>
                    <value>56654</value>
                </sharesOwnedFollowingTransaction>
            </postTransactionAmounts>
            <ownershipNature>
                <directOrIndirectOwnership>
                    <value>I</value>
                    <footnoteId id="F3"/>
                </directOrIndirectOwnership>
                <natureOfOwnership>
                    <value>by spouse</value>
                </natureOfOwnership>
            </ownershipNature>
        </nonDerivativeTransaction>
        <nonDerivativeTransaction>
            <securityTitle>
                <value>Common Stock</value>
            </securityTitle>
            <transactionDate>
                <value>2018-12-10</value>
            </transactionDate>
            <transactionCoding>
                <transactionFormType>4</transactionFormType>
                <transactionCode>S</transactionCode>
                <equitySwapInvolved>0</equitySwapInvolved>
                <footnoteId id="F1"/>
            </transactionCoding>
            <transactionAmounts>
                <transactionShares>
                    <value>5700</value>
                </transactionShares>
                <transactionPricePerShare>
                    <value>113.59</value>
                    <footnoteId id="F4"/>
                </transactionPricePerShare>
                <transactionAcquiredDisposedCode>
                    <value>D</value>
                </transactionAcquiredDisposedCode>
            </transactionAmounts>
            <postTransactionAmounts>
                <sharesOwnedFollowingTransaction>
                    <value>50954</value>
                </sharesOwnedFollowingTransaction>
            </postTransactionAmounts>
            <ownershipNature>
                <directOrIndirectOwnership>
                    <value>I</value>
                    <footnoteId id="F3"/>
                </directOrIndirectOwnership>
                <natureOfOwnership>
                    <value>by spouse</value>
                </natureOfOwnership>
            </ownershipNature>
        </nonDerivativeTransaction>
        <nonDerivativeHolding>
            <securityTitle>
                <value>Common Stock</value>
            </securityTitle>
            <postTransactionAmounts>
                <sharesOwnedFollowingTransaction>
                    <value>26562</value>
                </sharesOwnedFollowingTransaction>
            </postTransactionAmounts>
            <ownershipNature>
                <directOrIndirectOwnership>
                    <value>D</value>
                </directOrIndirectOwnership>
            </ownershipNature>
        </nonDerivativeHolding>
        <nonDerivativeHolding>
            <securityTitle>
                <value>Common Stock</value>
            </securityTitle>
            <postTransactionAmounts>
                <sharesOwnedFollowingTransaction>
                    <value>1180</value>
                </sharesOwnedFollowingTransaction>
            </postTransactionAmounts>
            <ownershipNature>
                <directOrIndirectOwnership>
                    <value>I</value>
                </directOrIndirectOwnership>
                <natureOfOwnership>
                    <value>401(k)</value>
                </natureOfOwnership>
            </ownershipNature>
        </nonDerivativeHolding>
        <nonDerivativeHolding>
            <securityTitle>
                <value>Common Stock</value>
            </securityTitle>
            <postTransactionAmounts>
                <sharesOwnedFollowingTransaction>
                    <value>1090</value>
                </sharesOwnedFollowingTransaction>
            </postTransactionAmounts>
            <ownershipNature>
                <directOrIndirectOwnership>
                    <value>I</value>
                    <footnoteId id="F3"/>
                </directOrIndirectOwnership>
                <natureOfOwnership>
                    <value>401(k) - by spouse</value>
                </natureOfOwnership>
            </ownershipNature>
        </nonDerivativeHolding>
    </nonDerivativeTable>

    <derivativeTable></derivativeTable>

    <footnotes>
        <footnote id="F1">The transaction reported in this Form 4 was effected pursuant to a Rule 10b5-1 trading plan adopted by the reporting person on November 9, 2018.</footnote>
        <footnote id="F2">This transaction was executed in multiple trades at prices ranging from $112.37 to $113.34. The price reported reflects the weighted average sale price. The reporting person hereby undertakes to provide upon request to the SEC staff, the issuer or a security holder of the issuer full information regarding the number of shares and prices at which the transaction was effected.</footnote>
        <footnote id="F3">Reporting person disclaims beneficial ownership of these shares.</footnote>
        <footnote id="F4">This transaction was executed in multiple trades at prices ranging from $113.45 to $113.60. The price reported reflects the weighted average sale price. The reporting person hereby undertakes to provide upon request to the SEC staff, the issuer or a security holder of the issuer full information regarding the number of shares and prices at which the transaction was effected.</footnote>
    </footnotes>

    <remarks></remarks>

    <ownerSignature>
        <signatureName>Crystal T. Williams for Myles O'Neill, authorization on file</signatureName>
        <signatureDate>2018-12-11</signatureDate>
    </ownerSignature>
</ownershipDocument>
