<?xml version="1.0"?>
<ownershipDocument>

    <schemaVersion>X0306</schemaVersion>

    <documentType>4</documentType>

    <periodOfReport>2019-01-11</periodOfReport>

    <issuer>
        <issuerCik>0000812348</issuerCik>
        <issuerName>CENTURY BANCORP INC</issuerName>
        <issuerTradingSymbol>CNBKA</issuerTradingSymbol>
    </issuer>

    <reportingOwner>
        <reportingOwnerId>
            <rptOwnerCik>0001246206</rptOwnerCik>
            <rptOwnerName>EVANGELISTA PAUL A</rptOwnerName>
        </reportingOwnerId>
        <reportingOwnerAddress>
            <rptOwnerStreet1>400 MYSTIC AVENUE</rptOwnerStreet1>
            <rptOwnerStreet2></rptOwnerStreet2>
            <rptOwnerCity>MEDFORD</rptOwnerCity>
            <rptOwnerState>MA</rptOwnerState>
            <rptOwnerZipCode>02155</rptOwnerZipCode>
            <rptOwnerStateDescription></rptOwnerStateDescription>
        </reportingOwnerAddress>
        <reportingOwnerRelationship>
            <isOfficer>1</isOfficer>
            <officerTitle>Executive Vice President</officerTitle>
        </reportingOwnerRelationship>
    </reportingOwner>

    <nonDerivativeTable>
        <nonDerivativeTransaction>
            <securityTitle>
                <value>401(k) Company Stock Fund</value>
            </securityTitle>
            <transactionDate>
                <value>2019-01-11</value>
            </transactionDate>
            <transactionCoding>
                <transactionFormType>4</transactionFormType>
                <transactionCode>P</transactionCode>
                <equitySwapInvolved>0</equitySwapInvolved>
            </transactionCoding>
            <transactionTimeliness></transactionTimeliness>
            <transactionAmounts>
                <transactionShares>
                    <value>25.0208</value>
                </transactionShares>
                <transactionPricePerShare>
                    <value>124.37</value>
                </transactionPricePerShare>
                <transactionAcquiredDisposedCode>
                    <value>A</value>
                </transactionAcquiredDisposedCode>
            </transactionAmounts>
            <postTransactionAmounts>
                <sharesOwnedFollowingTransaction>
                    <value>2055.0331</value>
                </sharesOwnedFollowingTransaction>
            </postTransactionAmounts>
            <ownershipNature>
                <directOrIndirectOwnership>
                    <value>D</value>
                </directOrIndirectOwnership>
            </ownershipNature>
        </nonDerivativeTransaction>
        <nonDerivativeHolding>
            <securityTitle>
                <value>Class A Common</value>
            </securityTitle>
            <postTransactionAmounts>
                <sharesOwnedFollowingTransaction>
                    <value>5856.5586</value>
                </sharesOwnedFollowingTransaction>
            </postTransactionAmounts>
            <ownershipNature>
                <directOrIndirectOwnership>
                    <value>D</value>
                </directOrIndirectOwnership>
            </ownershipNature>
        </nonDerivativeHolding>
    </nonDerivativeTable>

    <footnotes></footnotes>

    <remarks>The 401k Stock Fund consists of units having a share and a cash component.  The price shown is that of a unit.</remarks>

    <ownerSignature>
        <signatureName>/s/ William P. Hornby, Attorney-In-Fact</signatureName>
        <signatureDate>2019-01-14</signatureDate>
    </ownerSignature>
</ownershipDocument>
