<?xml version="1.0"?>
<ownershipDocument>

    <schemaVersion>X0306</schemaVersion>

    <documentType>4</documentType>

    <periodOfReport>2019-01-21</periodOfReport>

    <notSubjectToSection16>0</notSubjectToSection16>

    <issuer>
        <issuerCik>0000883975</issuerCik>
        <issuerName>Microbot Medical Inc.</issuerName>
        <issuerTradingSymbol>MBOT</issuerTradingSymbol>
    </issuer>

    <reportingOwner>
        <reportingOwnerId>
            <rptOwnerCik>0001399318</rptOwnerCik>
            <rptOwnerName>Burell Scott R</rptOwnerName>
        </reportingOwnerId>
        <reportingOwnerAddress>
            <rptOwnerStreet1>C/O MICROBOT MEDICAL INC.</rptOwnerStreet1>
            <rptOwnerStreet2>25 RECREATION PARK DRIVE, UNIT 108</rptOwnerStreet2>
            <rptOwnerCity>HINGHAM</rptOwnerCity>
            <rptOwnerState>MA</rptOwnerState>
            <rptOwnerZipCode>02043</rptOwnerZipCode>
            <rptOwnerStateDescription></rptOwnerStateDescription>
        </reportingOwnerAddress>
        <reportingOwnerRelationship>
            <isDirector>1</isDirector>
            <isOfficer>0</isOfficer>
            <isTenPercentOwner>0</isTenPercentOwner>
            <isOther>0</isOther>
            <officerTitle></officerTitle>
            <otherText></otherText>
        </reportingOwnerRelationship>
    </reportingOwner>

    <derivativeTable>
        <derivativeTransaction>
            <securityTitle>
                <value>Stock Option (Right to Buy)</value>
            </securityTitle>
            <conversionOrExercisePrice>
                <value>8.60</value>
            </conversionOrExercisePrice>
            <transactionDate>
                <value>2019-01-21</value>
            </transactionDate>
            <deemedExecutionDate></deemedExecutionDate>
            <transactionCoding>
                <transactionFormType>4</transactionFormType>
                <transactionCode>A</transactionCode>
                <equitySwapInvolved>0</equitySwapInvolved>
            </transactionCoding>
            <transactionTimeliness></transactionTimeliness>
            <transactionAmounts>
                <transactionShares>
                    <value>2326</value>
                </transactionShares>
                <transactionPricePerShare>
                    <value>0</value>
                </transactionPricePerShare>
                <transactionAcquiredDisposedCode>
                    <value>A</value>
                </transactionAcquiredDisposedCode>
            </transactionAmounts>
            <exerciseDate>
                <footnoteId id="F1"/>
            </exerciseDate>
            <expirationDate>
                <value>2029-01-21</value>
            </expirationDate>
            <underlyingSecurity>
                <underlyingSecurityTitle>
                    <value>Common Stock, par value $0.01 per share</value>
                </underlyingSecurityTitle>
                <underlyingSecurityShares>
                    <value>2326</value>
                </underlyingSecurityShares>
            </underlyingSecurity>
            <postTransactionAmounts>
                <sharesOwnedFollowingTransaction>
                    <value>2326</value>
                </sharesOwnedFollowingTransaction>
            </postTransactionAmounts>
            <ownershipNature>
                <directOrIndirectOwnership>
                    <value>D</value>
                </directOrIndirectOwnership>
            </ownershipNature>
        </derivativeTransaction>
    </derivativeTable>

    <footnotes>
        <footnote id="F1">The options vest as follows and in accordance with the terms of the Issuer's 2017 Equity Incentive Plan: (a) on March 4, 2019, the option shall vest and shall become exercisable with respect to 25% of the common stock; and (b) on a quarterly basis over the next 30 months, the option shall equally vest and become exercisable with respect to the remaining 75% of the common stock.</footnote>
    </footnotes>

    <ownerSignature>
        <signatureName>/s/ Scott Burell</signatureName>
        <signatureDate>2019-01-23</signatureDate>
    </ownerSignature>
</ownershipDocument>
